koalified/__init__.py
koalified/_version.py
koalified/compile.py
koalified/schema.py
koalified/types.py
koalified-0.1.0.dist-info/LICENSE
koalified-0.1.0.dist-info/METADATA
koalified-0.1.0.dist-info/WHEEL
koalified-0.1.0.dist-info/top_level.txt
koalified-0.1.0.dist-info/RECORD
