Metadata-Version: 2.1
Name: koalified
Version: 0.1.0
Summary: For when truth is a little fuzzy.
Home-page: https://github.com/domaintools/koalified_python
Author: DomainTools
Author-email: timothy@domaintools.com
License: MIT
Keywords: Python,Python3
Platform: UNKNOWN
Classifier: Development Status :: 6 - Mature
Classifier: Intended Audience :: Developers
Classifier: Natural Language :: English
Classifier: Environment :: Console
Classifier: License :: OSI Approved :: MIT License
Classifier: Programming Language :: Python
Classifier: Programming Language :: Python :: 3
Classifier: Programming Language :: Python :: 3.5
Classifier: Programming Language :: Python :: 3.6
Classifier: Programming Language :: Python :: 3.7
Classifier: Topic :: Software Development :: Libraries
Classifier: Topic :: Utilities
Requires-Dist: PyYAML
Requires-Dist: validators
Requires-Dist: requests
Requires-Dist: xxhash
Requires-Dist: phonenumbers
Requires-Dist: pycountry
Requires-Dist: arrow
Provides-Extra: cython
Requires-Dist: Cython (>=0.24) ; extra == 'cython'
